{
  "nodes":[
    {"name":"Australia","group":1, "perCapitaGdp": 46600, "color":"#2929a3"},
    {"name":"China", "group":2,"perCapitaGdp": 12900, "color":"#999999"},
    {"name":"Denmark","group":3, "perCapitaGdp": 44300, "color":"#cc2900"},
    {"name":"France","group":4, "perCapitaGdp": 40500, "color":"#bf4080"},
    {"name":"Netherlands","group":5, "perCapitaGdp": 47400, "color":"orange"},
    {"name":"New Zealand","group":6, "perCapitaGdp": 35000, "color":"#2929a3"},
    {"name":"Norway","group":7, "perCapitaGdp": 65900, "color":"#336699"},
    {"name":"Great Britain","group":8, "perCapitaGdp": 37700, "color":"#2929a3"},
    {"name":"United States","group":9, "perCapitaGdp": 54800, "color":"#2929a3"},
    {"name":"Ashmore and Cartier Islands","group":1, "perCapitaGdp": null, "color":"#2929a3"},
    {"name":"Christmas Island","group":1, "perCapitaGdp": null, "color":"#2929a3"},
    {"name":"Cocos (Keeling) Islands","group":1, "perCapitaGdp": null, "color":"#2929a3"},
    {"name":"Coral Sea Islands","group":1, "perCapitaGdp": null, "color":"#2929a3"},
    {"name":"Heard Island and McDonald Islands","group":1, "perCapitaGdp": null, "color":"#2929a3"},
    {"name":"Norfolk Island","group":1, "perCapitaGdp": null, "color":"#2929a3"},
    {"name":"Hong Kong","group":2, "perCapitaGdp": 55200, "color":"#999999"},
    {"name":"Macau","group":2, "perCapitaGdp": 88700, "color":"#999999"},
    {"name":"Faroe Islands","group":3, "perCapitaGdp": 55400, "color":"#cc2900"},
    {"name":"Greenland","group":3, "perCapitaGdp": 38400, "color":"#cc2900"},
    {"name":"Clipperton Island","group":4, "perCapitaGdp": null, "color":"#bf4080"},
    {"name":"French Polynesia","group":4, "perCapitaGdp": 40400, "color":"#bf4080"},
    {"name":"French Southern and Antarctic Lands","group":4, "perCapitaGdp": null, "color":"#bf4080"},
    {"name":"New Caledonia","group":4, "perCapitaGdp": 38800, "color":"#bf4080"},
    {"name":"Saint Barthelemy","group":4, "perCapitaGdp": null, "color":"#bf4080"},
    {"name":"Saint Martin","group":4, "perCapitaGdp": 19300, "color":"#bf4080"},
    {"name":"Saint Pierre and Miquelon","group":4, "perCapitaGdp": 34900, "color":"#bf4080"},
    {"name":"Wallis and Futuna","group":4, "perCapitaGdp": 3800, "color":"#bf4080"},
    {"name":"Aruba","group":5, "perCapitaGdp": 25300, "color":"orange"},
    {"name":"Curacao","group":5, "perCapitaGdp": 15000, "color":"orange"},
    {"name":"Sint Maarten","group":5, "perCapitaGdp": 66800, "color":"orange"},
    {"name":"Cook Islands","group":6, "perCapitaGdp": 9100, "color":"#2929a3"},
    {"name":"Niue","group":6, "perCapitaGdp": 5800, "color":"#2929a3"},
    {"name":"Tokelau","group":6, "perCapitaGdp": 1000, "color":"#2929a3"},
    {"name":"Bouvet Island","group":7, "perCapitaGdp": null, "color":"#336699"},
    {"name":"Jan Mayan","group":7, "perCapitaGdp": null, "color":"#336699"},
    {"name":"Svalbard","group":7, "perCapitaGdp": null, "color":"#336699"},
    {"name":"Akrotiri","group":8, "perCapitaGdp": null, "color":"#2929a3"},
    {"name":"Anguilla","group":8, "perCapitaGdp": 12200, "color":"#2929a3"},
    {"name":"Bermuda","group":8, "perCapitaGdp": 86000, "color":"#2929a3"},
    {"name":"British Indian Ocean Territory","group":8, "perCapitaGdp": null, "color":"#2929a3"},
    {"name":"British Virgin Islands","group":8, "perCapitaGdp": 42300, "color":"#2929a3"},
    {"name":"Cayman Islands","group":8, "perCapitaGdp": 43800, "color":"#2929a3"},
    {"name":"Dhekelia (Sovereign Base)","group":8, "perCapitaGdp": null, "color":"#2929a3"},
    {"name":"Falkland Islands","group":8, "perCapitaGdp": 38300, "color":"#2929a3"},
    {"name":"Gibraltar","group":8, "perCapitaGdp": 43000, "color":"#2929a3"},
    {"name":"Guernsey","group":8, "perCapitaGdp": 44600, "color":"#2929a3"},
    {"name":"Isle of Man","group":8, "perCapitaGdp": 83100, "color":"#2929a3"},
    {"name":"Montserrat","group":8, "perCapitaGdp": 8500, "color":"#2929a3"},
    {"name":"Pitcairn Islands","group":8, "perCapitaGdp": null, "color":"#2929a3"},
    {"name":"Saint Helena, Ascension, and Tristan da Cunha","group":8, "perCapitaGdp": 7800, "color":"#2929a3"},
    {"name":"South Georgia and the South Sandwich Islands","group":8, "perCapitaGdp": null, "color":"#2929a3"},
    {"name":"Turks and Caicos Islands","group":8, "perCapitaGdp": 29100, "color":"#2929a3"},
    {"name":"American Samoa","group":9, "perCapitaGdp": 8000, "color":"#2929a3"},
    {"name":"Guam","group":9, "perCapitaGdp": 28700, "color":"#2929a3"},
    {"name":"Navassa Island","group":9, "perCapitaGdp": null, "color":"#2929a3"},
    {"name":"Northern Mariana Islands","group":9, "perCapitaGdp": 13600, "color":"#2929a3"},
    {"name":"Puerto Rico","group":9, "perCapitaGdp": 16300, "color":"#2929a3"},
    {"name":"U.S. Virgin Islands","group":9, "perCapitaGdp": 14500, "color":"#2929a3"},
    {"name":"Wake Island","group":9, "perCapitaGdp": null, "color":"#2929a3"},
    {"name":"Baker Island (US Pacific Island Wildlife Refuge)","group":9, "perCapitaGdp": null, "color":"#2929a3"},
    {"name":"Howland Island (US Pacific Island Wildlife Refuge)","group":9, "perCapitaGdp": null, "color":"#2929a3"},
    {"name":"Jarvis Island (US Pacific Island Wildlife Refuge)","group":9, "perCapitaGdp": null, "color":"#2929a3"},
    {"name":"Johnston Atoll (US Pacific Island Wildlife Refuge)","group":9, "perCapitaGdp": null, "color":"#2929a3"},
    {"name":"Kingman Reef (US Pacific Island Wildlife Refuge)","group":9, "perCapitaGdp": null, "color":"#2929a3"},
    {"name":"Midway Islands (US Pacific Island Wildlife Refuge)","group":9, "perCapitaGdp": null, "color":"#2929a3"},
    {"name":"Palmyra Atoll (US Pacific Island Wildlife Refuge)","group":9, "perCapitaGdp": null, "color":"#2929a3"}
  ],
  "links":[
    {"source":9,"target":0,"value":"none"},
    {"source":10,"target":0,"value":"none"},
    {"source":11,"target":0,"value":"none"},
    {"source":12,"target":0,"value":"none"},
    {"source":13,"target":0,"value":"none"},
    {"source":14,"target":0,"value":"none"},
    {"source":15,"target":1,"value":"none"},
    {"source":16,"target":1,"value":"none"},
    {"source":17,"target":2,"value":"none"},
    {"source":18,"target":2,"value":"none"},
    {"source":19,"target":3,"value":"none"},
    {"source":20,"target":3,"value":"none"},
    {"source":21,"target":3,"value":"none"},
    {"source":22,"target":3,"value":"none"},
    {"source":23,"target":3,"value":"none"},
    {"source":24,"target":3,"value":"none"},
    {"source":25,"target":3,"value":"none"},
    {"source":26,"target":3,"value":"none"},
    {"source":27, "target":4, "value":"none"},
    {"source":28, "target":4, "value":"none"},
    {"source":29, "target":4, "value":"none"},
    {"source":30, "target":5, "value":"none"},
    {"source":31, "target":5, "value":"none"},
    {"source":32, "target":5, "value":"none"},
    {"source":33, "target":6, "value":"none"},
    {"source":34, "target":6, "value":"none"},
    {"source":35, "target":6, "value":"none"},
    {"source":36, "target":7, "value":"none"},
    {"source":37, "target":7, "value":"none"},
    {"source":38, "target":7, "value":"none"},
    {"source":39, "target":7, "value":"none"},
    {"source":40, "target":7, "value":"none"},
    {"source":41, "target":7, "value":"none"},
    {"source":42, "target":7, "value":"none"},
    {"source":43, "target":7, "value":"none"},
    {"source":44, "target":7, "value":"none"},
    {"source":45, "target":7, "value":"none"},
    {"source":46, "target":7, "value":"none"},
    {"source":47, "target":7, "value":"none"},
    {"source":48, "target":7, "value":"none"},
    {"source":49, "target":7, "value":"none"},
    {"source":50, "target":7, "value":"none"},
    {"source":51, "target":7, "value":"none"},
    {"source":52, "target":8, "value":"none"},
    {"source":53, "target":8, "value":"none"},
    {"source":54, "target":8, "value":"none"},
    {"source":55, "target":8, "value":"none"},
    {"source":56, "target":8, "value":"none"},
    {"source":57, "target":8, "value":"none"},
    {"source":58, "target":8, "value":"none"},
    {"source":59, "target":8, "value":"none"},
    {"source":60, "target":8, "value":"none"},
    {"source":61, "target":8, "value":"none"},
    {"source":62, "target":8, "value":"none"},
    {"source":63, "target":8, "value":"none"},
    {"source":64, "target":8, "value":"none"},
    {"source":65, "target":8, "value":"none"},
    {"source":7, "target":0, "value":[5,5]},
    {"source":7, "target":5, "value":[5,5]},
    {"source":7, "target":8, "value":[5,5]},
    {"source":7, "target":15, "value":[5,5]}
  ]
}